nget-0.0.3.dist-info/METADATA
nget-0.0.3.dist-info/WHEEL
nget-0.0.3.dist-info/entry_points.txt
nget-0.0.3.dist-info/licenses/LICENSE
nget/__init__.py
nget/nget.py
nget-0.0.3.dist-info/RECORD
