Metadata-Version: 2.1
Name: nget
Version: 0.0.3
Summary: A simple package for safely retrieving nested values from data structures using a sequence of keys or indexes.
Author-Email: alcortazzo <ipodarock@gmail.com>
License: MIT
Classifier: Development Status :: 5 - Production/Stable
Classifier: Intended Audience :: Developers
Classifier: License :: OSI Approved :: MIT License
Project-URL: Repository, https://github.com/alcortazzo/nget.git
Project-URL: Issues, https://github.com/alcortazzo/nget/issues
Requires-Python: >=3.9
